[
  {
    "UserName": "john_doe",
    "DateOfBirth": "1990-05-15",
    "KnownAs": "John",
    "Gender": "Male",
    "Introduction": "Hello, I'm John!",
    "LookingFor": "Looking for new friends",
    "Interests": "Reading, hiking, coding",
    "City": "New York",
    "Country": "USA",
    "Created": "2023-01-01T12:00:00Z",
    "LastActive": "2023-11-30T18:30:00Z",
    "Photos": [
      {
        "Url": "john_photo1.jpg",
        "IsMain": true
      },
      {
        "Url": "john_photo2.jpg",
        "IsMain": false
      }
    ]
  },
  {
    "UserName": "jane_doe",
    "DateOfBirth": "1988-09-22",
    "KnownAs": "Jane",
    "Gender": "Female",
    "Introduction": "Hi, I'm Jane!",
    "LookingFor": "Looking for a serious relationship",
    "Interests": "Traveling, photography, cooking",
    "City": "Los Angeles",
    "Country": "USA",
    "Created": "2023-02-15T10:30:00Z",
    "LastActive": "2023-11-29T20:45:00Z",
    "Photos": [
      {
        "Url": "jane_photo1.jpg",
        "IsMain": true
      },
      {
        "Url": "jane_photo2.jpg",
        "IsMain": false
      }
    ]
  },
  {
    "UserName": "alex_smith",
    "DateOfBirth": "1985-12-10",
    "KnownAs": "Alex",
    "Gender": "Male",
    "Introduction": "Greetings from Alex!",
    "LookingFor": "Exploring new opportunities",
    "Interests": "Music, technology, sports",
    "City": "San Francisco",
    "Country": "USA",
    "Created": "2023-03-20T08:15:00Z",
    "LastActive": "2023-11-28T15:20:00Z",
    "Photos": [
      {
        "Url": "alex_photo1.jpg",
        "IsMain": true
      },
      {
        "Url": "alex_photo2.jpg",
        "IsMain": false
      }
    ]
  },
  {
    "UserName": "emily_wilson",
    "DateOfBirth": "1992-07-18",
    "KnownAs": "Emily",
    "Gender": "Female",
    "Introduction": "Hey there, I'm Emily!",
    "LookingFor": "Connecting with like-minded people",
    "Interests": "Art, literature, travel",
    "City": "Chicago",
    "Country": "USA",
    "Created": "2023-04-10T14:45:00Z",
    "LastActive": "2023-11-27T12:10:00Z",
    "Photos": [
      {
        "Url": "emily_photo1.jpg",
        "IsMain": true
      },
      {
        "Url": "emily_photo2.jpg",
        "IsMain": false
      }
    ]
  },
  {
    "UserName": "michael_jones",
    "DateOfBirth": "1987-03-25",
    "KnownAs": "Michael",
    "Gender": "Male",
    "Introduction": "Hello, I'm Michael!",
    "LookingFor": "Networking and making friends",
    "Interests": "Gaming, coding, movies",
    "City": "Seattle",
    "Country": "USA",
    "Created": "2023-05-05T16:20:00Z",
    "LastActive": "2023-11-26T17:55:00Z",
    "Photos": [
      {
        "Url": "michael_photo1.jpg",
        "IsMain": true
      },
      {
        "Url": "michael_photo2.jpg",
        "IsMain": false
      }
    ]
  }
]
